{"cameraMode":{"drawMode":0,"name":"Shaded","section":"Shading Mode"},"sceneLighting":false,"audioPlay":false,"sceneViewState":{"m_AlwaysRefresh":false,"showFog":true,"showSkybox":false,"showFlares":true,"showImageEffects":true,"showParticleSystems":true,"showVisualEffectGraphs":true,"m_FxEnabled":true},"in2DMode":false,"pivot":{"x":24.807191848754884,"y":-1.9256432056427003,"z":-16.05459976196289},"rotation":{"x":0.08351359516382218,"y":0.6028545498847961,"z":-0.06365890800952912,"w":0.7908996343612671},"size":9.680874824523926,"orthographic":false}